{
    "Id": "620225049fa64b949ee9e692",
    "Name": "Carmel T4 1",
    "Root": "45406fea03c045dc812a18df",
    "Items": [
        {
            "_id": "45406fea03c045dc812a18df",
            "_tpl": "66ba249b102a9dd6040a6e7e",
            "upd": {
                "Repairable": {
                    "MaxDurability": 100,
                    "Durability": 100
                },
                "Foldable": {
                    "Folded": false
                },
                "FireMode": {
                    "FireMode": "single"
                }
            }
        },
        {
            "_id": "9f9911ca68df43a7889ae51e",
            "_tpl": "66ba253030ea88abba95c7ed",
            "slotId": "mod_pistol_grip",
            "parentId": "45406fea03c045dc812a18df"
        },
        {
            "_id": "ba3fb2d87c5646af9d0f00aa",
            "_tpl": "66ba264700cd37059ee31f36",
            "slotId": "mod_barrel",
            "parentId": "45406fea03c045dc812a18df"
        },
        {
            "_id": "f4595c003c124036b652d944",
            "_tpl": "55d4887d4bdc2d962f8b4570",
            "slotId": "mod_magazine",
            "parentId": "45406fea03c045dc812a18df"
        },
        {
            "_id": "c52c989675494e9b985334d8",
            "_tpl": "66ba268d7f9d8cfb6d0fbf77",
            "slotId": "mod_stock",
            "parentId": "45406fea03c045dc812a18df"
        },
        {
            "_id": "f27d886ec4ff41b4a0c24868",
            "_tpl": "6386120cd6baa055ad1e201c",
            "slotId": "mod_muzzle",
            "parentId": "ba3fb2d87c5646af9d0f00aa"
        },
        {
            "_id": "43e8325b654246e1bb75df0d",
            "_tpl": "66ba262124e3cd6bbf4715a8",
            "slotId": "mod_tactical_001",
            "parentId": "45406fea03c045dc812a18df"
        },
        {
            "_id": "e0fa61f055b545f884faea1a",
            "_tpl": "66ba25ed9195d94a8f131b2d",
            "slotId": "mod_tactical_002",
            "parentId": "45406fea03c045dc812a18df"
        },
        {
            "_id": "c37d69a8f80647feb29292b0",
            "_tpl": "66ba25d71a26d54d7504d785",
            "slotId": "mod_tactical_003",
            "parentId": "45406fea03c045dc812a18df"
        },
        {
            "_id": "81588f9ce51940e68b8b3253",
            "_tpl": "59f9d81586f7744c7506ee62",
            "parentId": "45406fea03c045dc812a18df",
            "slotId": "mod_scope"
        },
        {
            "_id": "08a21cb90aee44ebb6a41e53",
            "_tpl": "638612b607dfed1ccb7206ba",
            "parentId": "f27d886ec4ff41b4a0c24868",
            "slotId": "mod_muzzle"
        }
    ],
    "Parent": "5447b5f14bdc2d61278b4567",
    "Factions": [
        "usec"
    ],
    "SpareMags": 3,
    "Weight": 1000
}
