{
    "Id": "ef4828481624499ebfc6f4a1",
    "Name": "RSASS T4",
    "Root": "4ca1d9507f57456b997c5a83",
    "Items": [
        {
            "_id": "4ca1d9507f57456b997c5a83",
            "_tpl": "5a367e5dc4a282000e49738f",
            "upd": {
                "Repairable": {
                    "MaxDurability": 100,
                    "Durability": 100
                },
                "FireMode": {
                    "FireMode": "single"
                }
            }
        },
        {
            "_id": "cedf763bc80b4f46a8ddb03c",
            "_tpl": "59db3a1d86f77429e05b4e92",
            "parentId": "4ca1d9507f57456b997c5a83",
            "slotId": "mod_pistol_grip"
        },
        {
            "_id": "299a84568db54273a38b6220",
            "_tpl": "5a3501acc4a282000d72293a",
            "parentId": "4ca1d9507f57456b997c5a83",
            "slotId": "mod_magazine"
        },
        {
            "_id": "daa8dd9cfdb14365a5e121de",
            "_tpl": "5c793fc42e221600114ca25d",
            "parentId": "4ca1d9507f57456b997c5a83",
            "slotId": "mod_stock"
        },
        {
            "_id": "0875f3ded39d494abc71d4b7",
            "_tpl": "5a329052c4a28200741e22d3",
            "parentId": "4ca1d9507f57456b997c5a83",
            "slotId": "mod_handguard"
        },
        {
            "_id": "f971080033ae4f2896abaacd",
            "_tpl": "5a34f7f1c4a2826c6e06d75d",
            "parentId": "4ca1d9507f57456b997c5a83",
            "slotId": "mod_barrel"
        },
        {
            "_id": "d83efbc4638d45509996cd0c",
            "_tpl": "5a1ead28fcdbcb001912fa9f",
            "parentId": "4ca1d9507f57456b997c5a83",
            "slotId": "mod_scope"
        },
        {
            "_id": "d8938f2493c9452a886c54b9",
            "_tpl": "5a1eaa87fcdbcb001865f75e",
            "parentId": "d83efbc4638d45509996cd0c",
            "slotId": "mod_scope"
        },
        {
            "_id": "64e0d3adaa42412dbd257c85",
            "_tpl": "5fb6564947ce63734e3fa1da",
            "parentId": "4ca1d9507f57456b997c5a83",
            "slotId": "mod_sight_rear",
            "upd": {
                "Sight": {
                    "ScopesCurrentCalibPointIndexes": [
                        0
                    ],
                    "ScopesSelectedModes": [
                        0
                    ],
                    "SelectedScope": 0,
                    "ScopeZoomValue": 0
                }
            }
        },
        {
            "_id": "48575b1353b641bfbcf92e34",
            "_tpl": "56eabf3bd2720b75698b4569",
            "parentId": "daa8dd9cfdb14365a5e121de",
            "slotId": "mod_stock_000"
        },
        {
            "_id": "4f3eb169f83044adad69cc82",
            "_tpl": "58d2912286f7744e27117493",
            "parentId": "48575b1353b641bfbcf92e34",
            "slotId": "mod_stock"
        },
        {
            "_id": "f6d69319d436416b9b8b13a6",
            "_tpl": "5c0102aa0db834001b734ba1",
            "parentId": "0875f3ded39d494abc71d4b7",
            "slotId": "mod_mount_004"
        },
        {
            "_id": "470cecef942940b389be65bf",
            "_tpl": "5c0102b20db834001d23eebc",
            "parentId": "f6d69319d436416b9b8b13a6",
            "slotId": "mod_foregrip"
        },
        {
            "_id": "020ae0f516ff4f3a9b94f6c3",
            "_tpl": "5b057b4f5acfc4771e1bd3e9",
            "parentId": "470cecef942940b389be65bf",
            "slotId": "mod_foregrip"
        },
        {
            "_id": "ed4f2191c2e4485c9e07012f",
            "_tpl": "5c0102aa0db834001b734ba1",
            "parentId": "0875f3ded39d494abc71d4b7",
            "slotId": "mod_mount_001"
        },
        {
            "_id": "4b85afebf2cf47c4bac7d1ff",
            "_tpl": "5c06595c0db834001a66af6c",
            "parentId": "ed4f2191c2e4485c9e07012f",
            "slotId": "mod_tactical"
        },
        {
            "_id": "1a69f0db5a33400d9885aa74",
            "_tpl": "5cf78496d7f00c065703d6ca",
            "parentId": "f971080033ae4f2896abaacd",
            "slotId": "mod_muzzle"
        },
        {
            "_id": "9e992d475e814d039be2704c",
            "_tpl": "5c878e9d2e2216000f201903",
            "parentId": "1a69f0db5a33400d9885aa74",
            "slotId": "mod_muzzle_000"
        },
        {
            "_id": "cc48412f8a17481fba3385f7",
            "_tpl": "5a34fbadc4a28200741e230a",
            "parentId": "f971080033ae4f2896abaacd",
            "slotId": "mod_gas_block"
        },
        {
            "_id": "ee601fcd630645bba6c435b3",
            "_tpl": "5fb6567747ce63734e3fa1dc",
            "parentId": "cc48412f8a17481fba3385f7",
            "slotId": "mod_sight_front",
            "upd": {
                "Sight": {
                    "ScopesCurrentCalibPointIndexes": [
                        0
                    ],
                    "ScopesSelectedModes": [
                        0
                    ],
                    "SelectedScope": 0,
                    "ScopeZoomValue": 0
                }
            }
        }
    ],
    "Parent": "5447b6194bdc2d67278b4567",
    "Factions": [
        "usec"
    ],
    "SpareMags": 2,
    "Weight": 1000
}
