{
    "Id": "04dfc04bd7344d95b5c62f97",
    "Name": "Tavor X95 9x19 T4 2",
    "Root": "d9ca0c82d0a14e309423d9e1",
    "Items": [
        {
            "_id": "d9ca0c82d0a14e309423d9e1",
            "_tpl": "67f425638b8cbfdc0cd1b5f2",
            "upd": {
                "Repairable": {
                    "MaxDurability": 100,
                    "Durability": 100
                },
                "Foldable": {
                    "Folded": false
                },
                "FireMode": {
                    "FireMode": "fullauto"
                }
            }
        },
        {
            "_id": "cd4a35b6d8d34b93a4fa897b",
            "_tpl": "67f4474195c2cf6ca66af881",
            "slotId": "mod_magazine",
            "parentId": "d9ca0c82d0a14e309423d9e1"
        },
        {
            "_id": "1bc56106a5a24b2ebe1fe62a",
            "_tpl": "67f2dd6203d3b7ec166970ef",
            "slotId": "mod_tactical_000",
            "parentId": "d9ca0c82d0a14e309423d9e1"
        },
        {
            "_id": "76554409340a41eb89570077",
            "_tpl": "67f2ddcd74c13fb90c2d7f1b",
            "slotId": "mod_tactical_001",
            "parentId": "d9ca0c82d0a14e309423d9e1"
        },
        {
            "_id": "74100d866b3349cb8ba00d99",
            "_tpl": "59f8a37386f7747af3328f06",
            "slotId": "mod_foregrip",
            "parentId": "d9ca0c82d0a14e309423d9e1"
        },
        {
            "_id": "7ebb24c6e10544f597a8ff58",
            "_tpl": "66a47ed3f97061a20b99f188",
            "slotId": "mod_sight_rear",
            "parentId": "d9ca0c82d0a14e309423d9e1",
            "upd": {
                "Sight": {
                    "ScopesCurrentCalibPointIndexes": [
                        0
                    ],
                    "ScopesSelectedModes": [
                        0
                    ],
                    "SelectedScope": 0
                }
            }
        },
        {
            "_id": "ac95e0382da34365a00d03c2",
            "_tpl": "66a47ed0df2ffbca58ebe5ed",
            "slotId": "mod_sight_front",
            "parentId": "d9ca0c82d0a14e309423d9e1",
            "upd": {
                "Sight": {
                    "ScopesCurrentCalibPointIndexes": [
                        0
                    ],
                    "ScopesSelectedModes": [
                        0
                    ],
                    "SelectedScope": 0
                }
            }
        },
        {
            "_id": "173f4e545b8c49e690cb2e6e",
            "_tpl": "58491f3324597764bc48fa02",
            "parentId": "d9ca0c82d0a14e309423d9e1",
            "slotId": "mod_scope"
        },
        {
            "_id": "d390df83e7554f91a7d875cb",
            "_tpl": "5c6165902e22160010261b28",
            "parentId": "d9ca0c82d0a14e309423d9e1",
            "slotId": "mod_muzzle"
        },
        {
            "_id": "6428ae34e73147fb90a41634",
            "_tpl": "6272370ee4013c5d7e31f418",
            "parentId": "1bc56106a5a24b2ebe1fe62a",
            "slotId": "mod_tactical"
        },
        {
            "_id": "b6abd56cf04c4438b7e817e5",
            "_tpl": "56def37dd2720bec348b456a",
            "parentId": "76554409340a41eb89570077",
            "slotId": "mod_tactical"
        }
    ],
    "Parent": "5447b5e04bdc2d62278b4567",
    "Factions": [
        "usec"
    ],
    "SpareMags": 3
}
