{
    "Id": "f3810cf672824b27b6850e8f",
    "Name": "TR-75 T4 2",
    "Root": "af154fef352a40478b224838",
    "Items": [
        {
            "_id": "af154fef352a40478b224838",
            "_tpl": "020020AB75AB750000000000",
            "upd": {
                "Repairable": {
                    "MaxDurability": 100,
                    "Durability": 100
                },
                "Foldable": {
                    "Folded": false
                },
                "FireMode": {
                    "FireMode": "fullauto"
                }
            }
        },
        {
            "_id": "80be01c596524339be3a055a",
            "_tpl": "649ec30cb013f04a700e60fb",
            "slotId": "mod_magazine",
            "parentId": "af154fef352a40478b224838"
        },
        {
            "_id": "ef9400ba25414e07a0e8ed62",
            "_tpl": "04BA4BAB75AB754B00000000",
            "slotId": "mod_barrel",
            "parentId": "af154fef352a40478b224838"
        },
        {
            "_id": "f701a0e8a37a47d8826b1b0c",
            "_tpl": "043143AB76AB764310000000",
            "slotId": "mod_stock",
            "parentId": "af154fef352a40478b224838"
        },
        {
            "_id": "a817f1e2bafa4011bfdd4f29",
            "_tpl": "58491f3324597764bc48fa02",
            "parentId": "af154fef352a40478b224838",
            "slotId": "mod_scope"
        },
        {
            "_id": "6a47787112b54e3e8ee9cff6",
            "_tpl": "041041AB76AB764100000000",
            "parentId": "af154fef352a40478b224838",
            "slotId": "mod_handguard"
        },
        {
            "_id": "cca8647c23854a3aa272d991",
            "_tpl": "044144AB76AB764410000000",
            "parentId": "af154fef352a40478b224838",
            "slotId": "mod_stock_000"
        },
        {
            "_id": "77710f6137a64842bb7cd766",
            "_tpl": "045145AB76AB764510000000",
            "parentId": "af154fef352a40478b224838",
            "slotId": "mod_pistol_grip"
        },
        {
            "_id": "b70055490dd649c5a26ea064",
            "_tpl": "5b057b4f5acfc4771e1bd3e9",
            "parentId": "6a47787112b54e3e8ee9cff6",
            "slotId": "mod_foregrip"
        },
        {
            "_id": "978d3935466d478899224c50",
            "_tpl": "6272370ee4013c5d7e31f418",
            "parentId": "6a47787112b54e3e8ee9cff6",
            "slotId": "mod_tactical_000"
        },
        {
            "_id": "130e9c9503ae4dc6aeff9cfd",
            "_tpl": "04BE4BAB75AB75EB00000000",
            "parentId": "ef9400ba25414e07a0e8ed62",
            "slotId": "mod_muzzle"
        },
        {
            "_id": "45fa0cbccfb541b6b45813d9",
            "_tpl": "615d8f5dd92c473c770212ef",
            "parentId": "130e9c9503ae4dc6aeff9cfd",
            "slotId": "mod_muzzle"
        },
        {
            "_id": "4e8b9b294a6f410c8d4cc222",
            "_tpl": "615d8f8567085e45ef1409ca",
            "parentId": "45fa0cbccfb541b6b45813d9",
            "slotId": "mod_muzzle"
        }
    ],
    "Parent": "5447b5f14bdc2d61278b4567",
    "Factions": [
        "bear"
    ]
}
